[{"id":"911245af.d07218","type":"tab","label":"Monitor IoT","disabled":false,"info":""},{"id":"4412e15f.2141b","type":"function","z":"911245af.d07218","name":"separacion","func":"\nvar outputmsg = [];\nvar values= msg.payload.trim().split(\",\");\nfor (var v in values)\n{\n    outputmsg.push({payload:values[v]})\n}\nreturn outputmsg;","outputs":6,"noerr":0,"initialize":"","finalize":"","libs":[],"x":290,"y":220,"wires":[["fc88c9ff.37ba18","5191d13d.ae74c"],["15d361e1.b0db4e","c417e661.c27808"],["dc45a41f.22ca88","eecd0839.9888b8"],["97bce6a4.31c3d8","a6b342a0.84868"],["7a7871f0.37e82","79b72668.7d1bc8"],["39e8677d.ec3588","191fdfd4.567d4"]]},{"id":"2c469715.229fe8","type":"serial in","z":"911245af.d07218","name":"Arduino","serial":"9ba05871.740a68","x":120,"y":220,"wires":[["4412e15f.2141b"]]},{"id":"15d361e1.b0db4e","type":"wiotp out","z":"911245af.d07218","authType":"d","qs":"false","qsDeviceId":"","deviceKey":"885c7e92.a4647","deviceType":"","deviceId":"","event":"Temperatura","format":"json","qos":"","name":"","x":590,"y":160,"wires":[]},{"id":"fc88c9ff.37ba18","type":"wiotp out","z":"911245af.d07218","authType":"d","qs":"false","qsDeviceId":"","deviceKey":"35ebd717.8a84b8","deviceType":"","deviceId":"","event":"Giroscopio","format":"json","qos":"","name":"","x":590,"y":80,"wires":[]},{"id":"dc45a41f.22ca88","type":"wiotp out","z":"911245af.d07218","authType":"d","qs":"false","qsDeviceId":"","deviceKey":"e1b11fb0.4add","deviceType":"","deviceId":"","event":"Oxímetro","format":"json","qos":"","name":"","x":580,"y":200,"wires":[]},{"id":"97bce6a4.31c3d8","type":"wiotp out","z":"911245af.d07218","authType":"d","qs":"false","qsDeviceId":"","deviceKey":"f06cf56d.e583d8","deviceType":"","deviceId":"","event":"Alcohol","format":"json","qos":"","name":"","x":580,"y":280,"wires":[]},{"id":"7a7871f0.37e82","type":"wiotp out","z":"911245af.d07218","authType":"d","qs":"false","qsDeviceId":"","deviceKey":"6f01f850.b41b78","deviceType":"","deviceId":"","event":"BPM","format":"json","qos":"","name":"","x":570,"y":360,"wires":[]},{"id":"39e8677d.ec3588","type":"wiotp out","z":"911245af.d07218","authType":"d","qs":"false","qsDeviceId":"","deviceKey":"bca39d2d.4cc2f","deviceType":"","deviceId":"","event":"Presion","format":"json","qos":"","name":"","x":580,"y":440,"wires":[]},{"id":"5191d13d.ae74c","type":"mqtt out","z":"911245af.d07218","name":"Giroscopio","topic":"Giroscopio","qos":"","retain":"","respTopic":"","contentType":"","userProps":"","correl":"","expiry":"","broker":"1a06b724.fa6279","x":590,"y":40,"wires":[]},{"id":"c417e661.c27808","type":"mqtt out","z":"911245af.d07218","name":"Temperatura","topic":"Temperatura","qos":"","retain":"","respTopic":"","contentType":"","userProps":"","correl":"","expiry":"","broker":"1a06b724.fa6279","x":590,"y":120,"wires":[]},{"id":"eecd0839.9888b8","type":"mqtt out","z":"911245af.d07218","name":"Oximetro","topic":"Oximetro","qos":"","retain":"","respTopic":"","contentType":"","userProps":"","correl":"","expiry":"","broker":"1a06b724.fa6279","x":580,"y":240,"wires":[]},{"id":"a6b342a0.84868","type":"mqtt out","z":"911245af.d07218","name":"Alcohol","topic":"Alcohol","qos":"","retain":"","respTopic":"","contentType":"","userProps":"","correl":"","expiry":"","broker":"1a06b724.fa6279","x":580,"y":320,"wires":[]},{"id":"79b72668.7d1bc8","type":"mqtt out","z":"911245af.d07218","name":"BPM","topic":"BPM","qos":"","retain":"","respTopic":"","contentType":"","userProps":"","correl":"","expiry":"","broker":"1a06b724.fa6279","x":570,"y":400,"wires":[]},{"id":"191fdfd4.567d4","type":"mqtt out","z":"911245af.d07218","name":"Presion","topic":"Presion","qos":"","retain":"","respTopic":"","contentType":"","userProps":"","correl":"","expiry":"","broker":"1a06b724.fa6279","x":580,"y":480,"wires":[]},{"id":"9ba05871.740a68","type":"serial-port","serialport":"COM3","serialbaud":"115200","databits":"8","parity":"none","stopbits":"1","waitfor":"","dtr":"none","rts":"none","cts":"none","dsr":"none","newline":"\\n","bin":"false","out":"char","addchar":"","responsetimeout":"10000"},{"id":"885c7e92.a4647","type":"wiotp-credentials","name":"","org":"2bgz2g","serverName":"","devType":"Sensor","devId":"Temperatura","keepalive":"60","cleansession":true,"tls":"","usetls":false},{"id":"35ebd717.8a84b8","type":"wiotp-credentials","name":"","org":"2bgz2g","serverName":"","devType":"Sensor","devId":"Giroscopio","keepalive":"60","cleansession":true,"tls":"","usetls":false},{"id":"e1b11fb0.4add","type":"wiotp-credentials","name":"","org":"2bgz2g","serverName":"","devType":"Sensor","devId":"Oximetro","keepalive":"60","cleansession":true,"tls":"","usetls":false},{"id":"f06cf56d.e583d8","type":"wiotp-credentials","name":"","org":"2bgz2g","serverName":"","devType":"Sensor","devId":"Alcohol","keepalive":"60","cleansession":true,"tls":"","usetls":false},{"id":"6f01f850.b41b78","type":"wiotp-credentials","name":"","org":"2bgz2g","serverName":"","devType":"Sensor","devId":"BPM","keepalive":"60","cleansession":true,"tls":"","usetls":false},{"id":"bca39d2d.4cc2f","type":"wiotp-credentials","name":"","org":"2bgz2g","serverName":"","devType":"Sensor","devId":"Presion","keepalive":"60","cleansession":true,"tls":"","usetls":false},{"id":"1a06b724.fa6279","type":"mqtt-broker","name":"","broker":"sensores.cloud.shiftr.io","port":"1883","clientid":"Node1","usetls":false,"protocolVersion":"4","keepalive":"60","cleansession":true,"birthTopic":"","birthQos":"0","birthPayload":"","birthMsg":{},"closeTopic":"","closeQos":"0","closePayload":"","closeMsg":{},"willTopic":"","willQos":"0","willPayload":"","willMsg":{},"sessionExpiry":""}]