[{"id":"2a660243.9752fe","type":"tab","label":"Flow 1","disabled":false,"info":""},{"id":"bea46952.654858","type":"cloudant out","z":"2a660243.9752fe","name":"","cloudant":"","database":"Giroscopio","service":"node-red-monitoriot-cloudant-1625468350221-68435","payonly":false,"operation":"insert","x":510,"y":100,"wires":[]},{"id":"23c24843.8aa288","type":"mqtt in","z":"2a660243.9752fe","name":"","topic":"Giroscopio","qos":"0","datatype":"auto","broker":"de35651e.c2aa38","nl":false,"rap":true,"rh":0,"x":240,"y":100,"wires":[["bea46952.654858"]]},{"id":"4f1b9f4f.53349","type":"mqtt in","z":"2a660243.9752fe","name":"","topic":"Temperatura","qos":"0","datatype":"auto","broker":"de35651e.c2aa38","nl":false,"rap":true,"rh":0,"x":250,"y":160,"wires":[["cd6a7136.eebd8"]]},{"id":"cd6a7136.eebd8","type":"cloudant out","z":"2a660243.9752fe","name":"","cloudant":"","database":"Temperatura","service":"node-red-monitoriot-cloudant-1625468350221-68435","payonly":false,"operation":"insert","x":510,"y":160,"wires":[]},{"id":"d6bf0d45.cc2fc","type":"cloudant out","z":"2a660243.9752fe","name":"","cloudant":"","database":"Oximetro","service":"node-red-monitoriot-cloudant-1625468350221-68435","payonly":false,"operation":"insert","x":500,"y":220,"wires":[]},{"id":"f9a7d212.0434","type":"mqtt in","z":"2a660243.9752fe","name":"","topic":"Oximetro","qos":"0","datatype":"auto","broker":"de35651e.c2aa38","nl":false,"rap":true,"rh":0,"x":240,"y":220,"wires":[["d6bf0d45.cc2fc"]]},{"id":"f4ef91b7.f9c31","type":"mqtt in","z":"2a660243.9752fe","name":"","topic":"Alcohol","qos":"0","datatype":"auto","broker":"de35651e.c2aa38","nl":false,"rap":true,"rh":0,"x":230,"y":280,"wires":[["34e08c74.1cb204"]]},{"id":"34e08c74.1cb204","type":"cloudant out","z":"2a660243.9752fe","name":"","cloudant":"","database":"Alcohol","service":"node-red-monitoriot-cloudant-1625468350221-68435","payonly":false,"operation":"insert","x":500,"y":280,"wires":[]},{"id":"e15b4e41.e872a","type":"cloudant out","z":"2a660243.9752fe","name":"","cloudant":"","database":"BPM","service":"node-red-monitoriot-cloudant-1625468350221-68435","payonly":false,"operation":"insert","x":490,"y":340,"wires":[]},{"id":"7d210406.dfb52c","type":"mqtt in","z":"2a660243.9752fe","name":"","topic":"BPM","qos":"0","datatype":"auto","broker":"de35651e.c2aa38","nl":false,"rap":true,"rh":0,"x":230,"y":340,"wires":[["e15b4e41.e872a"]]},{"id":"a6087075.3edfb","type":"mqtt in","z":"2a660243.9752fe","name":"","topic":"Presion","qos":"0","datatype":"auto","broker":"de35651e.c2aa38","nl":false,"rap":true,"rh":0,"x":230,"y":400,"wires":[["4a1c3b23.202994"]]},{"id":"4a1c3b23.202994","type":"cloudant out","z":"2a660243.9752fe","name":"","cloudant":"","database":"Presion","service":"node-red-monitoriot-cloudant-1625468350221-68435","payonly":false,"operation":"insert","x":500,"y":400,"wires":[]},{"id":"de35651e.c2aa38","type":"mqtt-broker","name":"","broker":"sensores.cloud.shiftr.io","port":"1883","clientid":"Node2","usetls":false,"protocolVersion":"4","keepalive":"60","cleansession":true,"birthTopic":"","birthQos":"0","birthPayload":"","birthMsg":{},"closeTopic":"","closeQos":"0","closePayload":"","closeMsg":{},"willTopic":"","willQos":"0","willPayload":"","willMsg":{},"sessionExpiry":""}]